{"reviewerID": "A11ZP93TJED4T6", "asin": "0972683275", "reviewerName": "Ryan", "helpful": [1, 8], "reviewtext": "The fact that the pivot point on this TV mount was not built straight caused the TV to tilt slightly when it was swung out.  there is no adjustment for it, so i had to make a choice for the tv to either be straight and level when it was pushed against the wall, or when it was out.  i do not recommend this wall mount.to it's benefit though, it was reasonably sturdy and easy to install.", "overall": 2.0, "summary": "poor manufacture quality..", "unixReviewTime": 1285891200, "reviewTime": "10 1, 2010"}