{"reviewerID": "A1QRUMZRWUEWEK", "asin": "B00000J506", "reviewerName": "David House", "helpful": [4, 5], "reviewtext": "Had mine since December 1999 but noticed that the battery failed after about 3 years, like the other poster wrote, APC didn't list a replacement at first but now they do and I finally got around to replacing it.  Battery type is RBC2 for those wondering.Solid unit, having a telephone line/out and USB controller is a plus.", "overall": 4.0, "summary": "Great item", "unixReviewTime": 1106611200, "reviewTime": "01 25, 2005"}