{"reviewerID": "A21WV6SJFB21AM", "asin": "B00000JDF5", "reviewerName": "MSI", "helpful": [0, 1], "reviewtext": "Like the title suggests, why would any comsumer want to pay more for a product that does exactly the same thing?  Sure, there may exist purists that really believe a more expensive patch cable yields better signal delivery, but they'll have a hard time convincing me of an iota of difference.  Belkin is a reliable name that produces a reliable product at a highly competitive price.  I would buy, and will buy, these cables again and again.", "overall": 5.0, "summary": "Why Pay More?", "unixReviewTime": 1356998400, "reviewTime": "01 1, 2013"}