{"reviewerID": "A1FISS9YFJCXVG", "asin": "B00000JDF6", "reviewerName": "A. Kite \"boardgirl148\"", "helpful": [6, 6], "reviewtext": "I just installed a network between my two home computers, and this cable did the job perfectly.  It worked just like it is supposed to, and the 50ft length gave me all the cable I needed, with plenty left in case I decide to re-arrange the desk locations.  WELL worth the $10.99 price.", "overall": 5.0, "summary": "It is perfect.", "unixReviewTime": 1134864000, "reviewTime": "12 18, 2005"}