{"reviewerID": "A3JX1D26WFEXOS", "asin": "B00000JDF6", "reviewerName": "S. Bains \"singh\"", "helpful": [1, 1], "reviewtext": "This 50ft cable is flawless, snagless, no more kinks in the cable.The connectors are nice and soft and I love the blue color.This cable works like a charm and well worth the price at 50ft length.Highly recommended - cheaper than Radio Shack!", "overall": 5.0, "summary": "Premade Belkin Blue RJ45 Ethernet Cable - Snagless Baby!", "unixReviewTime": 1246320000, "reviewTime": "06 30, 2009"}