{"reviewerID": "A339ZN69W7N8PW", "asin": "B00001P4XH", "reviewerName": "Malinger Now", "helpful": [0, 0], "reviewtext": "Not sturdy but has lasted a year so far without problems. Even the cheapie in-line volume control has not created any noise problems. The price is right and this extension can be used with any headset. I think Koss will replace the cord free if it goes bad.", "overall": 4.0, "summary": "indispensible with short-cord phones", "unixReviewTime": 1250380800, "reviewTime": "08 16, 2009"}