{"reviewerID": "A2VUAICVS9XW35", "asin": "B00001P4XH", "reviewerName": "Sulligo \"Sulligo\"", "helpful": [0, 0], "reviewtext": "I have a Koss Headphone but leaning back in my chair was not quite long enough plus the volume control is very handy to make a quick volume control when needing to make quick volume controls as well as getting some more space.  The quality is very good with the headset and volume control.", "overall": 5.0, "summary": "Perfect For Listening To Audio On My PC", "unixReviewTime": 1375056000, "reviewTime": "07 29, 2013"}