{"reviewerID": "APOFQFXC8K645", "asin": "B0000226L0", "reviewerName": "Augustin A. Julien", "helpful": [0, 0], "reviewtext": "The shortwave radio is great. Very light weight and the main reason is for times in hurricanes when Electrical companies shuts down the power. I also purchased some eneloop AA rechargeable batteries to use with this shortwave radio.Very good for listening to other stations globally. Highly recommended for everyone at home,individuals camping and all others involved in some form of technology with radios.", "overall": 5.0, "summary": "Sangean ATS-404", "unixReviewTime": 1362960000, "reviewTime": "03 11, 2013"}