{"reviewerID": "AZSH7IFNZR62F", "asin": "B000023VW2", "reviewerName": "alex", "helpful": [2, 2], "reviewtext": "Yes, it greatly improves reception when attached to a telescopic antenna using the included clip. It gave me air traffic and SW. Wish it came with BNC adaptor though. Good for the price for a lazy guy like me. I guess you can get the same results with a long wire and a curtain clip.", "overall": 4.0, "summary": "improves sw reception", "unixReviewTime": 1369958400, "reviewTime": "05 31, 2013"}