{"reviewerID": "A283A424XAZCGX", "asin": "B000028F42", "reviewerName": "Cajundego \"Cajundego\"", "helpful": [3, 3], "reviewtext": "This is a great adapter/converter for international travel.  with a trip to several european countries & the UK, this was just what we needed. The only issue i had was w/ the weight.  it's rather heavy so we chose to put it on our carry on which we then had to deal w/.  i would buy this same one again though", "overall": 4.0, "summary": "Only draw back", "unixReviewTime": 1181865600, "reviewTime": "06 15, 2007"}