{"reviewerID": "A236XRE6MLXPKY", "asin": "B00003CWDH", "reviewerName": "David D.", "helpful": [0, 0], "reviewtext": "I rated it 5 stars because it is a great protector for the price.  You have ample ways of hooking up all your pieces.  Of course, this one is discontinued but I'm sure they made the newer model even better.  Don't know if it actually works because we haven't been hit by lightening or anything.  I have faith though.", "overall": 5.0, "summary": "Don't know if it works", "unixReviewTime": 1388102400, "reviewTime": "12 27, 2013"}