{"reviewerID": "A2XHVJXV58MHVL", "asin": "9573212919", "reviewerName": "Eric L. Parker", "helpful": [1, 1], "reviewtext": "Works as advertised. I needed a replacement for the internal drive on my Lenovo Y510 which had failed. Since the failure on the internal drive had happened before, I didn't want to deal with that again. Having an external drive is a little unhandy but once the OS had been loaded on it, an internal drive would be rarely needed.", "overall": 5.0, "summary": "External USB", "unixReviewTime": 1395360000, "reviewTime": "03 21, 2014"}