{"reviewerID": "A1U29HNXYN3TIB", "asin": "B00004T1XE", "reviewerName": "Jen", "helpful": [1, 1], "reviewtext": "I got this for power outage times, but find I use it in the shower and in random moments where I feel a good song is what I need. It also reminds me of my grandparents house where they always had one just like this (only metal) sitting in their bathroom. As a kid I would always play around with it, antenna and tuner dial, it was fun.", "overall": 5.0, "summary": "For power outages", "unixReviewTime": 1369267200, "reviewTime": "05 23, 2013"}