{"reviewerID": "A3GFS9L5GENQC7", "asin": "B00004T8R2", "reviewerName": "CR \"wondraone\"", "helpful": [0, 0], "reviewtext": "I wear hearing aids so unless I remove them, I cannot use ear buds. That works okay sometimes. But if I am about during the day and want to listen to my iTunes on my iPhone, I use the Panasonic headphones. They do not give me &#34;feedback&#34; as I expected and they are light weight.", "overall": 5.0, "summary": "Work very well", "unixReviewTime": 1380672000, "reviewTime": "10 2, 2013"}