{"reviewerID": "A1BUH3JUQ1MLOO", "asin": "B00004T8R2", "reviewerName": "Lauren R. \"Lodybean\"", "helpful": [0, 0], "reviewtext": "I purchased these with a few other sets of headphones and these had the worst sound out of all of them.  So muffled! I had read through a ton of the reviews on these and I thought I had a winner, but NO.  Don't bother with these.  The mid tones and treble sound like there being played under water.  Bleh.", "overall": 2.0, "summary": "Terrible sound", "unixReviewTime": 1378771200, "reviewTime": "09 10, 2013"}