{"reviewerID": "AFTMJLMVGC26P", "asin": "B00004THCX", "reviewerName": "Ted Hunger", "helpful": [0, 0], "reviewtext": "why I got this lens ill never know I may have a problem with buying lenses , yeah that's it. got this used on ebay with the hope it would be sharp....wrong! it was soft through out, if you can get this lens for free that's a deal. don't waste your cash if you like good looking photos.", "overall": 2.0, "summary": "soft....soft", "unixReviewTime": 1401321600, "reviewTime": "05 29, 2014"}