{"reviewerID": "AS21S3XF7XEG1", "asin": "B00004THDE", "reviewerName": "Tom N", "helpful": [5, 5], "reviewtext": "Great optics. Surprisingly bright and excellent for star gazing. I can actually see the moons of Jupiter with them.Issues- Protective caps don't stay on.. ever- Sucks up batteries pretty quickly- A bit heavyStill 5 stars. One of my all-time favorite expensive purchases.[update]To get caps to stay on, purchase UV filters for the lens. These lens fit standard camera filters size 52mm. Then the caps fit nicely. Also, protects the lens from accidental scratches.", "overall": 5.0, "summary": "Owned a pair for 3 years now", "unixReviewTime": 1319760000, "reviewTime": "10 28, 2011"}