{"reviewerID": "A6X2M9YBL9OYY", "asin": "B00004TZF9", "reviewerName": "Tom F", "helpful": [7, 7], "reviewtext": "These color coded tags help identify the connection to and from a device if you use many pieces of equipment.  A bag of six is just enough for the basic home user.  It uses velcro fasteners.  Length can be cut it fit. No place to write any names or purpose.  Color identification only.", "overall": 3.0, "summary": "Equipment Tag", "unixReviewTime": 1363478400, "reviewTime": "03 17, 2013"}